aladhan_mcp/__init__.py
aladhan_mcp/server.py
aladhan_mcp/utils.py
aladhan_mcp/tools/__init__.py
aladhan_mcp/tools/calendars.py
aladhan_mcp/tools/date_conversion.py
aladhan_mcp/tools/prayer_times.py
aladhan_mcp/tools/qibla.py
aladhan_mcp-0.1.1.dist-info/METADATA
aladhan_mcp-0.1.1.dist-info/WHEEL
aladhan_mcp-0.1.1.dist-info/entry_points.txt
aladhan_mcp-0.1.1.dist-info/licenses/LICENSE
aladhan_mcp-0.1.1.dist-info/RECORD
