Metadata-Version: 2.4
Name: aladhan-mcp
Version: 0.1.1
Summary: Model Context Protocol server for Aladhan prayer times API
Project-URL: Homepage, https://github.com/rawsab/aladhan-MCP-server
Project-URL: Repository, https://github.com/rawsab/aladhan-MCP-server
Project-URL: Issues, https://github.com/rawsab/aladhan-MCP-server/issues
Author-email: Rawsab Said <rawsab04@gmail.com>
License-Expression: MIT
License-File: LICENSE
Keywords: aladhan,api,islamic,mcp,prayer-times
Classifier: Development Status :: 4 - Beta
Classifier: Intended Audience :: Developers
Classifier: License :: OSI Approved :: MIT License
Classifier: Programming Language :: Python :: 3
Classifier: Programming Language :: Python :: 3.8
Classifier: Programming Language :: Python :: 3.9
Classifier: Programming Language :: Python :: 3.10
Classifier: Programming Language :: Python :: 3.11
Classifier: Programming Language :: Python :: 3.12
Requires-Python: >=3.8
Requires-Dist: asyncio
Requires-Dist: httpx>=0.24.0
Requires-Dist: mcp>=1.0.0
Provides-Extra: dev
Requires-Dist: black>=23.0.0; extra == 'dev'
Requires-Dist: flake8>=6.0.0; extra == 'dev'
Requires-Dist: isort>=5.12.0; extra == 'dev'
Requires-Dist: mypy>=1.0.0; extra == 'dev'
Requires-Dist: pytest-asyncio>=0.21.0; extra == 'dev'
Requires-Dist: pytest>=7.0.0; extra == 'dev'
